{
	"metadata": {
		"version": 4.5,
		"type": "BufferGeometry",
		"generator": "BufferGeometry.toJSON"
	},
	"uuid": "66B2966B-8AB3-4129-BCC7-7EE7F456D3FC",
	"type": "BufferGeometry",
	"data": {
		"attributes": {
			"position": {
				"itemSize": 3,
				"type": "Float32Array",
				"array": [-0.889071,-0.023379,-0.259706,-0.893602,-0.208566,-0.13825,-0.925932,-0.017561,-0.027136],
				"normalized": false
			},
			"normal": {
				"itemSize": 3,
				"type": "Float32Array",
				"array": [-0.985033,-0.077031,-0.154194,-0.985033,-0.077031,-0.154194,-0.985033,-0.077031,-0.154194],
				"normalized": false
			},
			"uv": {
				"itemSize": 2,
				"type": "Float32Array",
				"array": [0,1,0,1,0,1],
				"normalized": false
			}
		},
		"index": {
			"type": "Uint16Array",
			"array": [0,1,2]
		},
		"boundingSphere": {
			"center": [-0.907502,-0.113064,-0.143421],
			"radius": 0.1516
		}
	}
}